README.rst
setup.cfg
setup.py
OMP_soil_database/__init__.py
OMP_soil_database/removal_functions.py
OMP_soil_database.egg-info/PKG-INFO
OMP_soil_database.egg-info/SOURCES.txt
OMP_soil_database.egg-info/dependency_links.txt
OMP_soil_database.egg-info/requires.txt
OMP_soil_database.egg-info/top_level.txt
testing/__init__.py
testing/test_removal_functions.py