Metadata-Version: 2.1
Name: OMP-soil-database
Version: 0.2.0
Summary: A python package for calculating the removal of microbial organisms in the subsurface
Home-page: https://github.com/KWR-Water/OMP_soil_database
Author: KWR Water Research Institute
Author-email: vincent.post@kwrwater.nl, martin.korevaar@kwrwater.nl, martin.van.der.schans@kwrwater.nl, steven.ros@kwrwater.nl
License: MIT
Project-URL: Source, https://github.com/KWR-Water/OMP_soil_database
Project-URL: Documentation, http://OMP_soil_database.readthedocs.io/en/latest/
Project-URL: Tracker, https://github.com/KWR-Water/OMP_soil_database/issues
Project-URL: Help, https://github.com/KWR-Water/OMP_soil_database/issues
Platform: UNKNOWN
Classifier: Development Status :: 4 - Beta
Classifier: Intended Audience :: Science/Research
Classifier: Intended Audience :: Other Audience
Classifier: License :: OSI Approved :: MIT License
Classifier: Programming Language :: Python :: 3.6
Classifier: Programming Language :: Python :: 3.7
Classifier: Topic :: Scientific/Engineering :: Hydrology
Requires-Python: >=3.7
